Metadata-Version: 2.1
Name: fluffygoggles
Version: 0.1.0
Summary: A Python app for taking a screenshot, reading the text with OCR, and copying the text to the clipboard. And it's free.
Home-page: https://github.com/asweigart/fluffygoggles
Author: Al Sweigart
Author-email: al@inventwithpython.com
License: MIT
Platform: UNKNOWN
Classifier: License :: OSI Approved :: MIT License
Classifier: Programming Language :: Python
Classifier: Programming Language :: Python :: 3
Classifier: Programming Language :: Python :: 3.6
Classifier: Programming Language :: Python :: 3.7
Classifier: Programming Language :: Python :: 3.8
Classifier: Programming Language :: Python :: 3.9
Classifier: Programming Language :: Python :: 3.10
License-File: LICENSE.txt
